airports/__init__.py
airports/airport_data.py
airports/data/airports.gz
airports/data/airports.json
airports_py-3.0.0.dist-info/licenses/LICENSE
tests/__init__.py
tests/test_airport_data.py
airports_py-3.0.0.dist-info/METADATA
airports_py-3.0.0.dist-info/WHEEL
airports_py-3.0.0.dist-info/top_level.txt
airports_py-3.0.0.dist-info/RECORD
