Metadata-Version: 2.4
Name: airports-py
Version: 3.0.0
Summary: A comprehensive library providing easy retrieval of airport data based on IATA, ICAO, city codes, country codes, and continents. Features geographic search, distance calculation, timezone lookup, and external links integration.
Home-page: https://aashishvanand.me/airport-data-js/
Author: Aashish Vivekanand
Author-email: aashishvanand@gmail.com
Project-URL: Source Code, https://github.com/aashishvanand/airports-py
Project-URL: Bug Reports, https://github.com/aashishvanand/airports-py/issues
Project-URL: Documentation, https://github.com/aashishvanand/airports-py#readme
Keywords: airport,iata,icao,data,library,aviation,travel,geography,lookup,codes,continent,city,country,flightradar24,radarbox,flightaware,distance,coordinates,timezone,search,autocomplete,filtering,geospatial,proximity,navigation
Classifier: Development Status :: 5 - Production/Stable
Classifier: Intended Audience :: Developers
Classifier: Topic :: Software Development :: Libraries :: Python Modules
Classifier: Topic :: Scientific/Engineering :: GIS
Classifier: Topic :: Database
Classifier: Programming Language :: Python :: 3
Classifier: Programming Language :: Python :: 3.6
Classifier: Programming Language :: Python :: 3.7
Classifier: Programming Language :: Python :: 3.8
Classifier: Programming Language :: Python :: 3.9
Classifier: Programming Language :: Python :: 3.10
Classifier: Programming Language :: Python :: 3.11
Classifier: Programming Language :: Python :: 3.12
Classifier: Programming Language :: Python :: 3.13
Classifier: License :: OSI Approved :: MIT License
Classifier: Operating System :: OS Independent
Requires-Python: >=3.6
License-File: LICENSE
Provides-Extra: dev
Requires-Dist: pytest>=7.0.0; extra == "dev"
Requires-Dist: pytest-cov>=4.0.0; extra == "dev"
Requires-Dist: build>=1.0.0; extra == "dev"
Requires-Dist: twine>=4.0.0; extra == "dev"
Dynamic: author
Dynamic: author-email
Dynamic: classifier
Dynamic: description
Dynamic: description-content-type
Dynamic: home-page
Dynamic: keywords
Dynamic: license-file
Dynamic: project-url
Dynamic: provides-extra
Dynamic: requires-python
Dynamic: summary
